artest/__init__.py
artest/__main__.py
artest/artest.py
artest/config/__init__.py
artest/config/_func_repo.py
artest/config/_id_generator.py
artest/config/_match_result.py
artest/config/_paths.py
artest/config/_pickler.py
artest/config/_printer.py
artest/config/_tc_quota.py
artest/types.py
py_artest-0.3.0.dist-info/METADATA
py_artest-0.3.0.dist-info/WHEEL
py_artest-0.3.0.dist-info/RECORD
