Metadata-Version: 2.1
Name: py-artest
Version: 0.3.0
Summary: Automated Regression Testing Framework for Python
Home-page: https://github.com/HYChou0515/py-artest
License: MIT
Keywords: regression-testing,automated-testing
Author: Chou Hung-Yi
Author-email: hychou.svm@gmail.com
Requires-Python: >=3.8
Classifier: Development Status :: 5 - Production/Stable
Classifier: Intended Audience :: Developers
Classifier: License :: OSI Approved :: MIT License
Classifier: Programming Language :: Python :: 3
Classifier: Programming Language :: Python :: 3.8
Classifier: Programming Language :: Python :: 3.9
Classifier: Programming Language :: Python :: 3.10
Classifier: Programming Language :: Python :: 3.11
Classifier: Programming Language :: Python :: 3.12
Classifier: Topic :: Software Development :: Quality Assurance
Classifier: Topic :: Software Development :: Testing
Provides-Extra: dill
Project-URL: Repository, https://github.com/HYChou0515/py-artest
